neuralib/cellpose/__init__.py
neuralib/cellpose/core.py
neuralib/deeplabcut/__init__.py
neuralib/deeplabcut/core.py
neuralib/facemap/__init__.py
neuralib/facemap/core.py
neuralib/facemap/plot.py
neuralib/facemap/util.py
neuralib/morpho/__init__.py
neuralib/morpho/swc.py
neuralib/scan/__init__.py
neuralib/scan/core.py
neuralib/scan/czi.py
neuralib/scan/lsm.py
neuralib/scanbox/__init__.py
neuralib/scanbox/core.py
neuralib/scanbox/view.py
neuralib/stardist/__init__.py
neuralib/stardist/base.py
neuralib/stardist/core.py
neuralib/stardist/run_2d.py
neuralib/suite2p/__init__.py
neuralib/suite2p/core.py
neuralib/suite2p/plot.py
neuralib/suite2p/signals.py
neuralib_parser-0.7.0.dist-info/licenses/LICENSE
neuralib_parser-0.7.0.dist-info/METADATA
neuralib_parser-0.7.0.dist-info/WHEEL
neuralib_parser-0.7.0.dist-info/top_level.txt
neuralib_parser-0.7.0.dist-info/RECORD
