Metadata-Version: 2.4
Name: neuralib-parser
Version: 0.7.0
Summary: Parsers for output from open-source packages or specific devices
Author-email: Yu-Ting Wei <ytsimon2004@gmail.com>, Ta-Shun Su <antoniost29@gmail.com>
License: BSD-3-Clause
Project-URL: Homepage, https://github.com/ytsimon2004/neuralib2
Project-URL: Documentation, https://neuralib2.readthedocs.io/en/latest/index.html
Project-URL: Repository, https://github.com/ytsimon2004/neuralib2
Project-URL: Issues, https://github.com/ytsimon2004/neuralib2/issues
Keywords: Parser,Segmentation,Morphology
Classifier: Programming Language :: Python :: 3.11
Classifier: Programming Language :: Python :: 3.12
Classifier: License :: OSI Approved :: BSD License
Classifier: Natural Language :: English
Classifier: Operating System :: OS Independent
Classifier: Topic :: Scientific/Engineering
Classifier: Intended Audience :: Science/Research
Classifier: Typing :: Typed
Requires-Python: <3.13,>=3.11
License-File: LICENSE
Requires-Dist: neuralib-utils[all]>=0.7.0
Requires-Dist: numpy
Provides-Extra: stardist
Requires-Dist: stardist; extra == "stardist"
Requires-Dist: roifile; extra == "stardist"
Requires-Dist: tensorflow; extra == "stardist"
Requires-Dist: numpy<2.0; extra == "stardist" and extra == "stardist"
Requires-Dist: napari; extra == "stardist"
Provides-Extra: suite2p
Requires-Dist: neuralib-imaging>=0.7.0; extra == "suite2p"
Provides-Extra: czi
Requires-Dist: aicspylibczi; extra == "czi"
Requires-Dist: xmltodict; extra == "czi"
Provides-Extra: sbx
Requires-Dist: sbxreader; extra == "sbx"
Provides-Extra: all
Requires-Dist: neuralib-parser[suite2p]; extra == "all"
Requires-Dist: neuralib-parser[sbx]; extra == "all"
Requires-Dist: tifffile; extra == "all"
Dynamic: license-file
